sirad/VERSION
sirad/__init__.py
sirad/__main__.py
sirad/config.py
sirad/dataset.py
sirad/dialect.py
sirad/exceptions.py
sirad/extract.py
sirad/process.py
sirad/readers.py
sirad/research.py
sirad/soundex.py
sirad/validate.py
tests/__init__.py
tests/test_process.py
tests/test_validation.py
sirad-0.3.2.dist-info/LICENSE.txt
sirad-0.3.2.dist-info/METADATA
sirad-0.3.2.dist-info/WHEEL
sirad-0.3.2.dist-info/entry_points.txt
sirad-0.3.2.dist-info/top_level.txt
sirad-0.3.2.dist-info/RECORD
