Metadata-Version: 2.1
Name: sirad
Version: 0.3.2
Summary: Secure Infrastructure for Research with Administrative Data
Home-page: https://github.com/ripl-org/sirad
Author: Mark Howison
Author-email: mhowison@ripl.org
Classifier: Development Status :: 3 - Alpha
Classifier: License :: Free for non-commercial use
Classifier: Intended Audience :: Science/Research
Classifier: Natural Language :: English
Classifier: Operating System :: POSIX :: Linux
Classifier: Programming Language :: Python :: 3.7
Classifier: Topic :: Scientific/Engineering
Provides: sirad
License-File: LICENSE.txt
Requires-Dist: openpyxl
Requires-Dist: pandas
Requires-Dist: PyYAML
Requires-Dist: usaddress
